{
  "meta": {
    "date": "20240301",
    "jcd": "04",
    "rno": 5,
    "title": "DMM.com杯",
    "decision": "逃げ",
    "weather_sky": "晴",
    "wind_dir": 17,
    "wind_speed_m": 0,
    "wave_height_cm": 3
  },
  "results": [
    {
      "rank": "1",
      "lane": "1",
      "racer_id": "4171",
      "racer_name": "榎 幸司",
      "time": "1′51″7",
      "st": "0.15",
      "course": 1
    },
    {
      "rank": "2",
      "lane": "3",
      "racer_id": "5047",
      "racer_name": "國分 将太郎",
      "time": "1′52″8",
      "st": "0.09",
      "course": 3
    },
    {
      "rank": "3",
      "lane": "2",
      "racer_id": "4367",
      "racer_name": "山口 修路",
      "time": "1′55″1",
      "st": "0.11",
      "course": 2
    },
    {
      "rank": "4",
      "lane": "6",
      "racer_id": "4091",
      "racer_name": "荒田 泰明",
      "time": "1′55″4",
      "st": "0.05",
      "course": 6
    },
    {
      "rank": "5",
      "lane": "4",
      "racer_id": "4979",
      "racer_name": "中野 夢斗",
      "st": "0.04",
      "course": 4
    },
    {
      "rank": "6",
      "lane": "5",
      "racer_id": "3591",
      "racer_name": "後藤 孝義",
      "st": "0.02",
      "course": 5
    }
  ],
  "start": [
    {
      "lane": 1,
      "st": 0.15
    },
    {
      "lane": 2,
      "st": 0.11
    },
    {
      "lane": 3,
      "st": 0.09
    },
    {
      "lane": 4,
      "st": 0.04
    },
    {
      "lane": 5,
      "st": 0.02
    },
    {
      "lane": 6,
      "st": 0.05
    }
  ],
  "refunds": [],
  "payouts": {
    "trifecta": {
      "combo": "1-3-2",
      "amount": 700,
      "popularity": 1
    },
    "trio": {
      "combo": "1=2=3",
      "amount": 230,
      "popularity": 1
    },
    "exacta": {
      "combo": "1-3",
      "amount": 250,
      "popularity": 1
    },
    "quinella": {
      "combo": "1=3",
      "amount": 290,
      "popularity": 1
    },
    "wide": [
      {
        "combo": "1=3",
        "amount": 170,
        "popularity": 3
      }
    ],
    "win": {
      "combo": "1",
      "amount": 170,
      "popularity": 0
    },
    "place": [
      {
        "combo": "1",
        "amount": 100,
        "popularity": 0
      }
    ]
  },
  "source_url": "https://www.boatrace.jp/owpc/pc/race/raceresult?rno=5&jcd=04&hd=20240301",
  "generated_at": "2025-11-07T22:46:19.891Z"
}