{
  "date": "20240103",
  "pid": "20",
  "race": "4R",
  "source": "https://www.boatrace.jp/owpc/pc/race/beforeinfo?hd=20240103&jcd=20&rno=4",
  "mode": "beforeinfo",
  "generatedAt": "2025-11-07T04:04:04.280Z",
  "weather": {
    "weatherCode": 0,
    "windSpeed": 2,
    "windDirNum": 12,
    "temperature": 9,
    "waterTemperature": 11,
    "waveHeight": 0.02,
    "stabilizer": 0,
    "weatherText": null,
    "windDirection": "西南西"
  },
  "entries": [
    {
      "lane": 1,
      "number": "4195",
      "name": "前川 守嗣",
      "weight": "53.8kg",
      "tenjiTime": "6.87",
      "tilt": "-0.5",
      "st": ".21",
      "stFlag": "",
      "normalized": {
        "weightKg": 53.8,
        "tenjiSec": 6.87,
        "tiltDeg": -0.5,
        "stSec": 0.21,
        "isF": 0
      }
    },
    {
      "lane": 2,
      "number": "4252",
      "name": "松下 哲也",
      "weight": "51.5kg",
      "tenjiTime": "6.84",
      "tilt": "-0.5",
      "st": ".09",
      "stFlag": "",
      "normalized": {
        "weightKg": 51.5,
        "tenjiSec": 6.84,
        "tiltDeg": -0.5,
        "stSec": 0.09,
        "isF": 0
      }
    },
    {
      "lane": 3,
      "number": "4936",
      "name": "戸敷 晃美",
      "weight": "46.5kg",
      "tenjiTime": "6.87",
      "tilt": "-0.5",
      "st": ".08",
      "stFlag": "",
      "normalized": {
        "weightKg": 46.5,
        "tenjiSec": 6.87,
        "tiltDeg": -0.5,
        "stSec": 0.08,
        "isF": 0
      }
    },
    {
      "lane": 4,
      "number": "5210",
      "name": "藤井 公人",
      "weight": "54.4kg",
      "tenjiTime": "6.87",
      "tilt": "0.0",
      "st": ".16",
      "stFlag": "",
      "normalized": {
        "weightKg": 54.4,
        "tenjiSec": 6.87,
        "tiltDeg": 0,
        "stSec": 0.16,
        "isF": 0
      }
    },
    {
      "lane": 5,
      "number": "4848",
      "name": "仲谷 颯仁",
      "weight": "52.1kg",
      "tenjiTime": "6.82",
      "tilt": "0.0",
      "st": ".07",
      "stFlag": "",
      "normalized": {
        "weightKg": 52.1,
        "tenjiSec": 6.82,
        "tiltDeg": 0,
        "stSec": 0.07,
        "isF": 0
      }
    },
    {
      "lane": 6,
      "number": "4180",
      "name": "上野 秀和",
      "weight": "55.7kg",
      "tenjiTime": "6.91",
      "tilt": "-0.5",
      "st": ".03",
      "stFlag": "",
      "normalized": {
        "weightKg": 55.7,
        "tenjiSec": 6.91,
        "tiltDeg": -0.5,
        "stSec": 0.03,
        "isF": 0
      }
    }
  ]
}