{
  "date": "20250208",
  "pid": "15",
  "race": "5R",
  "source": "https://www.boatrace.jp/owpc/pc/race/beforeinfo?hd=20250208&jcd=15&rno=5",
  "mode": "beforeinfo",
  "generatedAt": "2025-11-07T07:53:26.162Z",
  "weather": {
    "weatherCode": 0,
    "windSpeed": 8,
    "windDirNum": 13,
    "temperature": 4,
    "waterTemperature": 10,
    "waveHeight": 0.08,
    "stabilizer": 1,
    "weatherText": null,
    "windDirection": "西"
  },
  "entries": [
    {
      "lane": 1,
      "number": "4757",
      "name": "山田 祐也",
      "weight": "52.7kg",
      "tenjiTime": "6.82",
      "tilt": "0.0",
      "st": "F.01",
      "stFlag": "F",
      "normalized": {
        "weightKg": 52.7,
        "tenjiSec": 6.82,
        "tiltDeg": 0,
        "stSec": 0.0001,
        "isF": 1
      }
    },
    {
      "lane": 2,
      "number": "4063",
      "name": "市橋 卓士",
      "weight": "52.9kg",
      "tenjiTime": "6.74",
      "tilt": "0.0",
      "st": "F.07",
      "stFlag": "F",
      "normalized": {
        "weightKg": 52.9,
        "tenjiSec": 6.74,
        "tiltDeg": 0,
        "stSec": 0.0007000000000000001,
        "isF": 1
      }
    },
    {
      "lane": 3,
      "number": "3304",
      "name": "烏野 賢太",
      "weight": "52.0kg",
      "tenjiTime": "6.85",
      "tilt": "0.0",
      "st": "F.02",
      "stFlag": "F",
      "normalized": {
        "weightKg": 52,
        "tenjiSec": 6.85,
        "tiltDeg": 0,
        "stSec": 0.0002,
        "isF": 1
      }
    },
    {
      "lane": 4,
      "number": "4571",
      "name": "菅 章哉",
      "weight": "52.0kg",
      "tenjiTime": "6.70",
      "tilt": "3.0",
      "st": "F.24",
      "stFlag": "F",
      "normalized": {
        "weightKg": 52,
        "tenjiSec": 6.7,
        "tiltDeg": 3,
        "stSec": 0.0024,
        "isF": 1
      }
    },
    {
      "lane": 5,
      "number": "4642",
      "name": "松尾 夏海",
      "weight": "47.0kg",
      "tenjiTime": "6.94",
      "tilt": "0.0",
      "st": "F.02",
      "stFlag": "F",
      "normalized": {
        "weightKg": 47,
        "tenjiSec": 6.94,
        "tiltDeg": 0,
        "stSec": 0.0002,
        "isF": 1
      }
    },
    {
      "lane": 6,
      "number": "3543",
      "name": "福田 雅一",
      "weight": "52.6kg",
      "tenjiTime": "6.84",
      "tilt": "0.0",
      "st": "F.02",
      "stFlag": "F",
      "normalized": {
        "weightKg": 52.6,
        "tenjiSec": 6.84,
        "tiltDeg": 0,
        "stSec": 0.0002,
        "isF": 1
      }
    }
  ]
}