{
  "date": "20240328",
  "pid": "17",
  "race": "1R",
  "source": "https://www.boatrace.jp/owpc/pc/race/beforeinfo?hd=20240328&jcd=17&rno=1",
  "mode": "beforeinfo",
  "generatedAt": "2025-11-07T10:46:07.547Z",
  "weather": {
    "weatherCode": 0,
    "windSpeed": 0,
    "windDirNum": null,
    "temperature": 10,
    "waterTemperature": 12,
    "waveHeight": 0.01,
    "stabilizer": 0,
    "weatherText": null,
    "windDirection": null
  },
  "entries": [
    {
      "lane": 1,
      "number": "3663",
      "name": "木山 和幸",
      "weight": "50.5kg",
      "tenjiTime": "6.75",
      "tilt": "-0.5",
      "st": "F.02",
      "stFlag": "F",
      "normalized": {
        "weightKg": 50.5,
        "tenjiSec": 6.75,
        "tiltDeg": -0.5,
        "stSec": 0.0002,
        "isF": 1
      }
    },
    {
      "lane": 2,
      "number": "4785",
      "name": "木幡 純也",
      "weight": "52.0kg",
      "tenjiTime": "6.76",
      "tilt": "-0.5",
      "st": ".09",
      "stFlag": "",
      "normalized": {
        "weightKg": 52,
        "tenjiSec": 6.76,
        "tiltDeg": -0.5,
        "stSec": 0.09,
        "isF": 0
      }
    },
    {
      "lane": 3,
      "number": "4277",
      "name": "金田 大輔",
      "weight": "52.0kg",
      "tenjiTime": "6.78",
      "tilt": "0.0",
      "st": "F.02",
      "stFlag": "F",
      "normalized": {
        "weightKg": 52,
        "tenjiSec": 6.78,
        "tiltDeg": 0,
        "stSec": 0.0002,
        "isF": 1
      }
    },
    {
      "lane": 4,
      "number": "3567",
      "name": "吉岡 誠",
      "weight": "55.0kg",
      "tenjiTime": "6.81",
      "tilt": "-0.5",
      "st": ".01",
      "stFlag": "",
      "normalized": {
        "weightKg": 55,
        "tenjiSec": 6.81,
        "tiltDeg": -0.5,
        "stSec": 0.01,
        "isF": 0
      }
    },
    {
      "lane": 5,
      "number": "4708",
      "name": "半田 尚也",
      "weight": "54.1kg",
      "tenjiTime": "6.85",
      "tilt": "-0.5",
      "st": ".08",
      "stFlag": "",
      "normalized": {
        "weightKg": 54.1,
        "tenjiSec": 6.85,
        "tiltDeg": -0.5,
        "stSec": 0.08,
        "isF": 0
      }
    },
    {
      "lane": 6,
      "number": "4834",
      "name": "浜本 裕己",
      "weight": "51.5kg",
      "tenjiTime": "6.75",
      "tilt": "0.5",
      "st": ".23",
      "stFlag": "",
      "normalized": {
        "weightKg": 51.5,
        "tenjiSec": 6.75,
        "tiltDeg": 0.5,
        "stSec": 0.23,
        "isF": 0
      }
    }
  ]
}