{
  "date": "20240101",
  "pid": "24",
  "race": "11R",
  "source": "https://www.boatrace.jp/owpc/pc/race/racelist?rno=11&jcd=24&hd=20240101",
  "mode": "program",
  "generatedAt": "2025-11-06T17:38:43.174Z",
  "entries": [
    {
      "lane": 1,
      "number": "3944",
      "name": "山口 裕二",
      "branch": "長崎",
      "grade": "A2",
      "age": 44,
      "weight": "52.1kg",
      "stats": {
        "national": "6.03 38.71 63.44",
        "local": "6.60 48.67 68.14",
        "motor": "16 29.63 51.11",
        "boat": "16 31.36 45.76"
      },
      "recent": {
        "entryCourses": [
          "3"
        ],
        "stList": [
          ".08"
        ],
        "results": [
          "１"
        ]
      }
    },
    {
      "lane": 2,
      "number": "4259",
      "name": "真庭 明志",
      "branch": "長崎",
      "grade": "A2",
      "age": 39,
      "weight": "52.0kg",
      "stats": {
        "national": "5.83 40.57 52.83",
        "local": "6.11 42.86 61.65",
        "motor": "12 29.93 48.18",
        "boat": "73 34.51 47.18"
      },
      "recent": {
        "entryCourses": [
          "5"
        ],
        "stList": [
          ".12"
        ],
        "results": [
          "２"
        ]
      }
    },
    {
      "lane": 3,
      "number": "4919",
      "name": "吉田 翔悟",
      "branch": "長崎",
      "grade": "A2",
      "age": 32,
      "weight": "52.0kg",
      "stats": {
        "national": "5.90 37.70 67.21",
        "local": "5.54 33.33 59.42",
        "motor": "23 34.59 48.87",
        "boat": "62 40.88 56.93"
      },
      "recent": {
        "entryCourses": [
          "6"
        ],
        "stList": [
          ".26"
        ],
        "results": [
          "５"
        ]
      }
    },
    {
      "lane": 4,
      "number": "4498",
      "name": "宮本 夏樹",
      "branch": "長崎",
      "grade": "B1",
      "age": 36,
      "weight": "53.5kg",
      "stats": {
        "national": "5.21 31.48 45.37",
        "local": "6.33 45.61 59.65",
        "motor": "53 25.00 43.75",
        "boat": "11 27.82 48.12"
      },
      "recent": {
        "entryCourses": [
          "3"
        ],
        "stList": [
          ".09"
        ],
        "results": [
          "５"
        ]
      }
    },
    {
      "lane": 5,
      "number": "5048",
      "name": "眞鳥 康太",
      "branch": "長崎",
      "grade": "B1",
      "age": 29,
      "weight": "53.8kg",
      "stats": {
        "national": "5.05 31.76 49.41",
        "local": "4.73 23.46 46.91",
        "motor": "28 31.39 53.28",
        "boat": "58 33.10 47.18"
      },
      "recent": {
        "entryCourses": [
          "3"
        ],
        "stList": [
          ".19"
        ],
        "results": [
          "５"
        ]
      }
    },
    {
      "lane": 6,
      "number": "4966",
      "name": "田川 大貴",
      "branch": "長崎",
      "grade": "A2",
      "age": 26,
      "weight": "53.5kg",
      "stats": {
        "national": "6.06 40.86 62.37",
        "local": "6.11 42.57 62.38",
        "motor": "60 33.09 47.06",
        "boat": "74 39.26 49.63"
      },
      "recent": {
        "entryCourses": [
          "4"
        ],
        "stList": [
          ".09"
        ],
        "results": [
          "３"
        ]
      }
    }
  ]
}