{
  "date": "20240105",
  "pid": "04",
  "race": "8R",
  "source": "https://www.boatrace.jp/owpc/pc/race/racelist?rno=8&jcd=04&hd=20240105",
  "mode": "program",
  "generatedAt": "2025-11-06T17:45:27.056Z",
  "entries": [
    {
      "lane": 1,
      "number": "4401",
      "name": "小林 泰",
      "branch": "東京",
      "grade": "A2",
      "age": 39,
      "weight": "53.4kg",
      "stats": {
        "national": "5.73 41.75 57.28",
        "local": "6.19 48.15 66.67",
        "motor": "66 31.03 49.14",
        "boat": "28 37.82 52.10"
      },
      "recent": {
        "entryCourses": [
          "3",
          "5",
          "2",
          "6",
          "4"
        ],
        "stList": [
          ".13",
          ".17",
          ".16",
          ".16",
          ".19"
        ],
        "results": [
          "２",
          "６",
          "３",
          "５",
          "６"
        ]
      }
    },
    {
      "lane": 2,
      "number": "3227",
      "name": "長岡 茂一",
      "branch": "東京",
      "grade": "B1",
      "age": 58,
      "weight": "53.1kg",
      "stats": {
        "national": "5.20 42.16 51.96",
        "local": "5.11 36.84 52.63",
        "motor": "34 39.17 58.33",
        "boat": "39 33.33 50.98"
      },
      "recent": {
        "entryCourses": [
          "5",
          "4",
          "4",
          "3"
        ],
        "stList": [
          ".11",
          ".24",
          ".17",
          ".11"
        ],
        "results": [
          "４",
          "３",
          "転",
          "４"
        ]
      }
    },
    {
      "lane": 3,
      "number": "3072",
      "name": "西田 靖",
      "branch": "東京",
      "grade": "B1",
      "age": 62,
      "weight": "52.0kg",
      "stats": {
        "national": "4.88 30.23 40.70",
        "local": "5.16 32.95 47.73",
        "motor": "13 36.52 55.65",
        "boat": "70 24.21 36.84"
      },
      "recent": {
        "entryCourses": [
          "2",
          "1",
          "2",
          "3"
        ],
        "stList": [
          ".31",
          ".21",
          ".15",
          ".26"
        ],
        "results": [
          "３",
          "３",
          "２",
          "３"
        ]
      }
    },
    {
      "lane": 4,
      "number": "3641",
      "name": "一瀬 明",
      "branch": "東京",
      "grade": "A1",
      "age": 52,
      "weight": "52.0kg",
      "stats": {
        "national": "6.29 44.80 70.40",
        "local": "6.00 46.34 65.85",
        "motor": "30 35.34 49.14",
        "boat": "41 42.98 66.67"
      },
      "recent": {
        "entryCourses": [
          "6",
          "3",
          "1",
          "5"
        ],
        "stList": [
          ".09",
          ".15",
          ".21",
          ".23"
        ],
        "results": [
          "３",
          "５",
          "１",
          "２"
        ]
      }
    },
    {
      "lane": 5,
      "number": "3293",
      "name": "宮内 由紀英",
      "branch": "東京",
      "grade": "B1",
      "age": 58,
      "weight": "51.5kg",
      "stats": {
        "national": "4.46 21.25 42.50",
        "local": "4.21 17.31 38.46",
        "motor": "51 43.36 56.64",
        "boat": "56 34.11 51.94"
      },
      "recent": {
        "entryCourses": [
          "1",
          "4",
          "3"
        ],
        "stList": [
          ".20",
          ".15",
          ".26"
        ],
        "results": [
          "５",
          "６",
          "５"
        ]
      }
    },
    {
      "lane": 6,
      "number": "3857",
      "name": "阿波 勝哉",
      "branch": "東京",
      "grade": "B1",
      "age": 50,
      "weight": "53.2kg",
      "stats": {
        "national": "4.43 14.71 41.18",
        "local": "5.01 20.25 50.63",
        "motor": "20 28.95 43.86",
        "boat": "30 28.46 50.00"
      },
      "recent": {
        "entryCourses": [
          "6",
          "6",
          "6",
          "6"
        ],
        "stList": [
          ".21",
          ".16",
          ".37",
          ".06"
        ],
        "results": [
          "６",
          "３",
          "２",
          "２"
        ]
      }
    }
  ]
}