{
  "date": "20240207",
  "pid": "06",
  "race": "6R",
  "source": "https://www.boatrace.jp/owpc/pc/race/racelist?rno=6&jcd=06&hd=20240207",
  "mode": "program",
  "generatedAt": "2025-11-06T18:58:37.455Z",
  "entries": [
    {
      "lane": 1,
      "number": "5269",
      "name": "山口 晃朋",
      "branch": "静岡",
      "grade": "B1",
      "age": 23,
      "weight": "52.1kg",
      "stats": {
        "national": "3.90 20.97 30.65",
        "local": "2.37 6.45 16.13",
        "motor": "2 44.25 62.64",
        "boat": "45 26.47 45.59"
      },
      "recent": {
        "entryCourses": [],
        "stList": [],
        "results": []
      }
    },
    {
      "lane": 2,
      "number": "4270",
      "name": "岸本 雄貴",
      "branch": "三重",
      "grade": "B1",
      "age": 41,
      "weight": "62.8kg",
      "stats": {
        "national": "3.68 17.58 32.97",
        "local": "3.83 27.78 27.78",
        "motor": "13 34.50 50.88",
        "boat": "71 41.54 61.54"
      },
      "recent": {
        "entryCourses": [],
        "stList": [],
        "results": []
      }
    },
    {
      "lane": 3,
      "number": "3392",
      "name": "小森 信雄",
      "branch": "三重",
      "grade": "B1",
      "age": 58,
      "weight": "52.0kg",
      "stats": {
        "national": "4.49 25.61 35.37",
        "local": "4.78 28.13 46.88",
        "motor": "35 39.66 55.17",
        "boat": "74 28.07 36.84"
      },
      "recent": {
        "entryCourses": [],
        "stList": [],
        "results": []
      }
    },
    {
      "lane": 4,
      "number": "2014",
      "name": "高塚 清一",
      "branch": "静岡",
      "grade": "B1",
      "age": 76,
      "weight": "52.0kg",
      "stats": {
        "national": "3.41 13.51 24.32",
        "local": "4.26 19.44 38.19",
        "motor": "44 26.49 40.40",
        "boat": "22 35.94 53.13"
      },
      "recent": {
        "entryCourses": [],
        "stList": [],
        "results": []
      }
    },
    {
      "lane": 5,
      "number": "3690",
      "name": "河合 三弘",
      "branch": "愛知",
      "grade": "B1",
      "age": 53,
      "weight": "52.5kg",
      "stats": {
        "national": "4.95 29.90 42.27",
        "local": "5.71 36.84 60.53",
        "motor": "43 27.85 43.67",
        "boat": "76 29.69 54.69"
      },
      "recent": {
        "entryCourses": [],
        "stList": [],
        "results": []
      }
    },
    {
      "lane": 6,
      "number": "5318",
      "name": "河内 一馬",
      "branch": "愛知",
      "grade": "B2",
      "age": 22,
      "weight": "54.7kg",
      "stats": {
        "national": "1.07 0.00 0.00",
        "local": "0.00 0.00 0.00",
        "motor": "6 27.91 41.86",
        "boat": "28 43.28 56.72"
      },
      "recent": {
        "entryCourses": [
          "6"
        ],
        "stList": [
          ".28"
        ],
        "results": [
          "６"
        ]
      }
    }
  ]
}