{
  "date": "20250218",
  "pid": "15",
  "race": "12R",
  "source": "https://www.boatrace.jp/owpc/pc/race/beforeinfo?hd=20250218&jcd=15&rno=12",
  "mode": "beforeinfo",
  "generatedAt": "2025-11-07T08:12:10.551Z",
  "weather": {
    "weatherCode": 0,
    "windSpeed": null,
    "windDirNum": null,
    "temperature": null,
    "waterTemperature": null,
    "waveHeight": null,
    "stabilizer": 0,
    "weatherText": null,
    "windDirection": null
  },
  "entries": [
    {
      "lane": 1,
      "number": "4930",
      "name": "佐藤 悠",
      "weight": "52.4kg",
      "tenjiTime": "",
      "tilt": "",
      "st": "",
      "stFlag": "",
      "normalized": {
        "weightKg": 52.4,
        "tenjiSec": null,
        "tiltDeg": null,
        "stSec": null,
        "isF": 0
      }
    },
    {
      "lane": 2,
      "number": "3357",
      "name": "福島 陽子",
      "weight": "48.0kg",
      "tenjiTime": "",
      "tilt": "",
      "st": "",
      "stFlag": "",
      "normalized": {
        "weightKg": 48,
        "tenjiSec": null,
        "tiltDeg": null,
        "stSec": null,
        "isF": 0
      }
    },
    {
      "lane": 3,
      "number": "4581",
      "name": "吉村 誠",
      "weight": "52.0kg",
      "tenjiTime": "",
      "tilt": "",
      "st": "",
      "stFlag": "",
      "normalized": {
        "weightKg": 52,
        "tenjiSec": null,
        "tiltDeg": null,
        "stSec": null,
        "isF": 0
      }
    },
    {
      "lane": 4,
      "number": "4436",
      "name": "渋谷 明憲",
      "weight": "52.2kg",
      "tenjiTime": "",
      "tilt": "",
      "st": "",
      "stFlag": "",
      "normalized": {
        "weightKg": 52.2,
        "tenjiSec": null,
        "tiltDeg": null,
        "stSec": null,
        "isF": 0
      }
    },
    {
      "lane": 5,
      "number": "4055",
      "name": "吉田 俊彦",
      "weight": "52.4kg",
      "tenjiTime": "",
      "tilt": "",
      "st": "",
      "stFlag": "",
      "normalized": {
        "weightKg": 52.4,
        "tenjiSec": null,
        "tiltDeg": null,
        "stSec": null,
        "isF": 0
      }
    },
    {
      "lane": 6,
      "number": "3627",
      "name": "井上 恵一",
      "weight": "51.5kg",
      "tenjiTime": "",
      "tilt": "",
      "st": "",
      "stFlag": "",
      "normalized": {
        "weightKg": 51.5,
        "tenjiSec": null,
        "tiltDeg": null,
        "stSec": null,
        "isF": 0
      }
    }
  ]
}