{
  "date": "20250218",
  "pid": "15",
  "race": "8R",
  "source": "https://www.boatrace.jp/owpc/pc/race/beforeinfo?hd=20250218&jcd=15&rno=8",
  "mode": "beforeinfo",
  "generatedAt": "2025-11-07T08:12:22.435Z",
  "weather": {
    "weatherCode": 0,
    "windSpeed": 9,
    "windDirNum": 13,
    "temperature": 5,
    "waterTemperature": 9,
    "waveHeight": 0.09,
    "stabilizer": 1,
    "weatherText": null,
    "windDirection": "西"
  },
  "entries": [
    {
      "lane": 1,
      "number": "4492",
      "name": "本多 宏和",
      "weight": "52.0kg",
      "tenjiTime": "6.62",
      "tilt": "-0.5",
      "st": ".09",
      "stFlag": "",
      "normalized": {
        "weightKg": 52,
        "tenjiSec": 6.62,
        "tiltDeg": -0.5,
        "stSec": 0.09,
        "isF": 0
      }
    },
    {
      "lane": 2,
      "number": "4581",
      "name": "吉村 誠",
      "weight": "52.0kg",
      "tenjiTime": "6.70",
      "tilt": "0.0",
      "st": ".00",
      "stFlag": "",
      "normalized": {
        "weightKg": 52,
        "tenjiSec": 6.7,
        "tiltDeg": 0,
        "stSec": 0,
        "isF": 0
      }
    },
    {
      "lane": 3,
      "number": "3553",
      "name": "平池 仁志",
      "weight": "52.1kg",
      "tenjiTime": "6.71",
      "tilt": "-0.5",
      "st": ".01",
      "stFlag": "",
      "normalized": {
        "weightKg": 52.1,
        "tenjiSec": 6.71,
        "tiltDeg": -0.5,
        "stSec": 0.01,
        "isF": 0
      }
    },
    {
      "lane": 4,
      "number": "3713",
      "name": "伊藤 誠二",
      "weight": "52.4kg",
      "tenjiTime": "6.67",
      "tilt": "0.0",
      "st": ".13",
      "stFlag": "",
      "normalized": {
        "weightKg": 52.4,
        "tenjiSec": 6.67,
        "tiltDeg": 0,
        "stSec": 0.13,
        "isF": 0
      }
    },
    {
      "lane": 5,
      "number": "4520",
      "name": "高倉 孝太",
      "weight": "52.0kg",
      "tenjiTime": "6.59",
      "tilt": "2.0",
      "st": "F.03",
      "stFlag": "F",
      "normalized": {
        "weightKg": 52,
        "tenjiSec": 6.59,
        "tiltDeg": 2,
        "stSec": 0.0003,
        "isF": 1
      }
    },
    {
      "lane": 6,
      "number": "5036",
      "name": "福田 翔吾",
      "weight": "52.1kg",
      "tenjiTime": "6.72",
      "tilt": "-0.5",
      "st": ".06",
      "stFlag": "",
      "normalized": {
        "weightKg": 52.1,
        "tenjiSec": 6.72,
        "tiltDeg": -0.5,
        "stSec": 0.06,
        "isF": 0
      }
    }
  ]
}