{
  "date": "20240214",
  "pid": "09",
  "race": "5R",
  "source": "https://www.boatrace.jp/owpc/pc/race/racelist?rno=5&jcd=09&hd=20240214",
  "mode": "program",
  "generatedAt": "2025-11-06T19:12:33.258Z",
  "entries": [
    {
      "lane": 1,
      "number": "4428",
      "name": "有賀 達也",
      "branch": "埼玉",
      "grade": "A1",
      "age": 38,
      "weight": "52.0kg",
      "stats": {
        "national": "6.41 43.70 65.19",
        "local": "6.85 52.17 71.74",
        "motor": "22 44.12 55.88",
        "boat": "50 21.57 33.33"
      },
      "recent": {
        "entryCourses": [
          "1",
          "5",
          "6",
          "2"
        ],
        "stList": [
          ".20",
          ".17",
          ".13",
          ".07"
        ],
        "results": [
          "１",
          "２",
          "４",
          "２"
        ]
      }
    },
    {
      "lane": 2,
      "number": "3674",
      "name": "岸 恵子",
      "branch": "徳島",
      "grade": "B1",
      "age": 51,
      "weight": "47.2kg",
      "stats": {
        "national": "5.26 32.14 48.81",
        "local": "5.55 39.47 52.63",
        "motor": "52 33.33 50.88",
        "boat": "31 41.30 56.52"
      },
      "recent": {
        "entryCourses": [
          "4",
          "3"
        ],
        "stList": [
          ".17",
          ".11"
        ],
        "results": [
          "５",
          "２"
        ]
      }
    },
    {
      "lane": 3,
      "number": "3605",
      "name": "中村 守成",
      "branch": "三重",
      "grade": "B1",
      "age": 52,
      "weight": "53.3kg",
      "stats": {
        "national": "4.66 21.98 39.56",
        "local": "5.22 33.33 46.49",
        "motor": "31 25.00 50.00",
        "boat": "76 32.14 50.00"
      },
      "recent": {
        "entryCourses": [
          "5",
          "1",
          "4"
        ],
        "stList": [
          ".17",
          ".21",
          ".16"
        ],
        "results": [
          "４",
          "２",
          "４"
        ]
      }
    },
    {
      "lane": 4,
      "number": "4224",
      "name": "大橋 栄里佳",
      "branch": "福岡",
      "grade": "B1",
      "age": 41,
      "weight": "48.0kg",
      "stats": {
        "national": "4.67 30.12 43.37",
        "local": "4.78 11.11 55.56",
        "motor": "32 34.21 57.89",
        "boat": "36 36.84 50.88"
      },
      "recent": {
        "entryCourses": [
          "6",
          "3",
          "5"
        ],
        "stList": [
          ".21",
          ".20",
          ".13"
        ],
        "results": [
          "５",
          "２",
          "５"
        ]
      }
    },
    {
      "lane": 5,
      "number": "5303",
      "name": "土井 歩夢",
      "branch": "福岡",
      "grade": "B1",
      "age": 20,
      "weight": "52.0kg",
      "stats": {
        "national": "3.01 5.88 17.65",
        "local": "0.00 0.00 0.00",
        "motor": "24 32.50 52.50",
        "boat": "71 16.22 27.03"
      },
      "recent": {
        "entryCourses": [
          "5",
          "6",
          "5"
        ],
        "stList": [
          ".22",
          ".18",
          ".20"
        ],
        "results": [
          "４",
          "５",
          "６"
        ]
      }
    },
    {
      "lane": 6,
      "number": "5048",
      "name": "眞鳥 康太",
      "branch": "長崎",
      "grade": "B1",
      "age": 29,
      "weight": "54.9kg",
      "stats": {
        "national": "5.07 31.52 47.83",
        "local": "5.40 40.00 40.00",
        "motor": "16 26.53 40.82",
        "boat": "68 25.53 42.55"
      },
      "recent": {
        "entryCourses": [
          "3",
          "5",
          "1"
        ],
        "stList": [
          ".09",
          ".25",
          ".21"
        ],
        "results": [
          "２",
          "５",
          "１"
        ]
      }
    }
  ]
}