{
  "date": "20190103",
  "pid": "06",
  "race": "12R",
  "source": "https://www.boatrace.jp/owpc/pc/race/beforeinfo?hd=20190103&jcd=06&rno=12",
  "mode": "beforeinfo",
  "generatedAt": "2025-11-06T13:48:30.864Z",
  "weather": {
    "weatherCode": 0,
    "windSpeed": 5,
    "windDirNum": 3,
    "temperature": 9,
    "waterTemperature": 10,
    "waveHeight": 0.03,
    "stabilizer": 1,
    "weatherText": null,
    "windDirection": "北東"
  },
  "entries": [
    {
      "lane": 1,
      "number": "3909",
      "name": "佐々木 康幸",
      "weight": "54.7kg",
      "tenjiTime": "6.81",
      "tilt": "0.0",
      "st": ".07",
      "stFlag": "",
      "normalized": {
        "weightKg": 54.7,
        "tenjiSec": 6.81,
        "tiltDeg": 0,
        "stSec": 0.07,
        "isF": 0
      }
    },
    {
      "lane": 2,
      "number": "3489",
      "name": "大場 敏",
      "weight": "51.0kg",
      "tenjiTime": "6.85",
      "tilt": "-0.5",
      "st": ".06",
      "stFlag": "",
      "normalized": {
        "weightKg": 51,
        "tenjiSec": 6.85,
        "tiltDeg": -0.5,
        "stSec": 0.06,
        "isF": 0
      }
    },
    {
      "lane": 3,
      "number": "2014",
      "name": "高塚 清一",
      "weight": "55.4kg",
      "tenjiTime": "6.88",
      "tilt": "0.0",
      "st": ".08",
      "stFlag": "",
      "normalized": {
        "weightKg": 55.4,
        "tenjiSec": 6.88,
        "tiltDeg": 0,
        "stSec": 0.08,
        "isF": 0
      }
    },
    {
      "lane": 4,
      "number": "4131",
      "name": "原 豊土",
      "weight": "52.8kg",
      "tenjiTime": "6.84",
      "tilt": "0.0",
      "st": ".09",
      "stFlag": "",
      "normalized": {
        "weightKg": 52.8,
        "tenjiSec": 6.84,
        "tiltDeg": 0,
        "stSec": 0.09,
        "isF": 0
      }
    },
    {
      "lane": 5,
      "number": "4342",
      "name": "谷野 錬志",
      "weight": "51.8kg",
      "tenjiTime": "6.87",
      "tilt": "-0.5",
      "st": ".08",
      "stFlag": "",
      "normalized": {
        "weightKg": 51.8,
        "tenjiSec": 6.87,
        "tiltDeg": -0.5,
        "stSec": 0.08,
        "isF": 0
      }
    },
    {
      "lane": 6,
      "number": "4417",
      "name": "服部 剛",
      "weight": "51.0kg",
      "tenjiTime": "6.86",
      "tilt": "0.0",
      "st": "F.03",
      "stFlag": "F",
      "normalized": {
        "weightKg": 51,
        "tenjiSec": 6.86,
        "tiltDeg": 0,
        "stSec": 0.0003,
        "isF": 1
      }
    }
  ]
}