{
  "date": "20240313",
  "pid": "19",
  "race": "4R",
  "source": "https://www.boatrace.jp/owpc/pc/race/beforeinfo?hd=20240313&jcd=19&rno=4",
  "mode": "beforeinfo",
  "generatedAt": "2025-11-07T10:19:01.238Z",
  "weather": {
    "weatherCode": 0,
    "windSpeed": 3,
    "windDirNum": 1,
    "temperature": 11,
    "waterTemperature": 12,
    "waveHeight": 0.03,
    "stabilizer": 0,
    "weatherText": null,
    "windDirection": "北"
  },
  "entries": [
    {
      "lane": 1,
      "number": "5189",
      "name": "藤原 早菜",
      "weight": "45.5kg",
      "tenjiTime": "6.88",
      "tilt": "0.0",
      "st": ".44",
      "stFlag": "",
      "normalized": {
        "weightKg": 45.5,
        "tenjiSec": 6.88,
        "tiltDeg": 0,
        "stSec": 0.44,
        "isF": 0
      }
    },
    {
      "lane": 2,
      "number": "4478",
      "name": "櫻本 あゆみ",
      "weight": "48.2kg",
      "tenjiTime": "6.90",
      "tilt": "-0.5",
      "st": ".17",
      "stFlag": "",
      "normalized": {
        "weightKg": 48.2,
        "tenjiSec": 6.9,
        "tiltDeg": -0.5,
        "stSec": 0.17,
        "isF": 0
      }
    },
    {
      "lane": 3,
      "number": "3188",
      "name": "日高 逸子",
      "weight": "46.5kg",
      "tenjiTime": "6.84",
      "tilt": "0.0",
      "st": ".08",
      "stFlag": "",
      "normalized": {
        "weightKg": 46.5,
        "tenjiSec": 6.84,
        "tiltDeg": 0,
        "stSec": 0.08,
        "isF": 0
      }
    },
    {
      "lane": 4,
      "number": "5250",
      "name": "嶋田 有里",
      "weight": "48.2kg",
      "tenjiTime": "6.96",
      "tilt": "-0.5",
      "st": ".25",
      "stFlag": "",
      "normalized": {
        "weightKg": 48.2,
        "tenjiSec": 6.96,
        "tiltDeg": -0.5,
        "stSec": 0.25,
        "isF": 0
      }
    },
    {
      "lane": 5,
      "number": "5248",
      "name": "本田 愛",
      "weight": "49.9kg",
      "tenjiTime": "6.94",
      "tilt": "0.0",
      "st": ".19",
      "stFlag": "",
      "normalized": {
        "weightKg": 49.9,
        "tenjiSec": 6.94,
        "tiltDeg": 0,
        "stSec": 0.19,
        "isF": 0
      }
    },
    {
      "lane": 6,
      "number": "4746",
      "name": "大豆生田 蒼",
      "weight": "47.0kg",
      "tenjiTime": "6.93",
      "tilt": "-0.5",
      "st": ".07",
      "stFlag": "",
      "normalized": {
        "weightKg": 47,
        "tenjiSec": 6.93,
        "tiltDeg": -0.5,
        "stSec": 0.07,
        "isF": 0
      }
    }
  ]
}