{
  "meta": {
    "date": "20250102",
    "jcd": "17",
    "rno": 3,
    "title": "第51回日刊スポーツ栄光楯新春広島ダービー ライブ&リプレイ レース場データ",
    "decision": null,
    "weather_sky": null,
    "wind_dir": "速",
    "wind_speed_m": 1,
    "wave_height_cm": null
  },
  "results": [],
  "start": [],
  "refunds": [
    "返還"
  ],
  "payouts": {
    "trifecta": {
      "combo": "2-1-4",
      "amount": 1870,
      "popularity": 7
    },
    "trio": {
      "combo": "1=2=4",
      "amount": 600,
      "popularity": 3
    },
    "exacta": {
      "combo": "2-1",
      "amount": 390,
      "popularity": 2
    },
    "quinella": {
      "combo": "1=2",
      "amount": 150,
      "popularity": 1
    },
    "wide": [
      {
        "combo": "1=2",
        "amount": 180,
        "popularity": 2
      }
    ],
    "win": {
      "combo": "2",
      "amount": 150,
      "popularity": 0
    },
    "place": [
      {
        "combo": "2",
        "amount": 100,
        "popularity": 0
      }
    ]
  },
  "source_url": "https://www.boatrace.jp/owpc/pc/race/raceresult?rno=3&jcd=17&hd=20250102",
  "generated_at": "2025-11-06T13:12:44.384Z"
}