{
  "date": "20240302",
  "pid": "07",
  "race": "2R",
  "source": "https://www.boatrace.jp/owpc/pc/race/beforeinfo?hd=20240302&jcd=07&rno=2",
  "mode": "beforeinfo",
  "generatedAt": "2025-11-07T09:58:38.566Z",
  "weather": {
    "weatherCode": 0,
    "windSpeed": 6,
    "windDirNum": 15,
    "temperature": 5,
    "waterTemperature": 9,
    "waveHeight": 0.04,
    "stabilizer": 0,
    "weatherText": null,
    "windDirection": "北西"
  },
  "entries": [
    {
      "lane": 1,
      "number": "5044",
      "name": "渡邉 健",
      "weight": "55.4kg",
      "tenjiTime": "6.56",
      "tilt": "-0.5",
      "st": "F.01",
      "stFlag": "F",
      "normalized": {
        "weightKg": 55.4,
        "tenjiSec": 6.56,
        "tiltDeg": -0.5,
        "stSec": 0.0001,
        "isF": 1
      }
    },
    {
      "lane": 2,
      "number": "5033",
      "name": "藤原 孝斗",
      "weight": "55.2kg",
      "tenjiTime": "6.64",
      "tilt": "-0.5",
      "st": "F.03",
      "stFlag": "F",
      "normalized": {
        "weightKg": 55.2,
        "tenjiSec": 6.64,
        "tiltDeg": -0.5,
        "stSec": 0.0003,
        "isF": 1
      }
    },
    {
      "lane": 3,
      "number": "5243",
      "name": "三馬 崇史",
      "weight": "54.8kg",
      "tenjiTime": "6.64",
      "tilt": "-0.5",
      "st": ".09",
      "stFlag": "",
      "normalized": {
        "weightKg": 54.8,
        "tenjiSec": 6.64,
        "tiltDeg": -0.5,
        "stSec": 0.09,
        "isF": 0
      }
    },
    {
      "lane": 4,
      "number": "5262",
      "name": "鈴木 章司",
      "weight": "52.0kg",
      "tenjiTime": "6.61",
      "tilt": "-0.5",
      "st": ".07",
      "stFlag": "",
      "normalized": {
        "weightKg": 52,
        "tenjiSec": 6.61,
        "tiltDeg": -0.5,
        "stSec": 0.07,
        "isF": 0
      }
    },
    {
      "lane": 5,
      "number": "4958",
      "name": "溝口 海義也",
      "weight": "53.6kg",
      "tenjiTime": "6.57",
      "tilt": "0.0",
      "st": ".03",
      "stFlag": "",
      "normalized": {
        "weightKg": 53.6,
        "tenjiSec": 6.57,
        "tiltDeg": 0,
        "stSec": 0.03,
        "isF": 0
      }
    },
    {
      "lane": 6,
      "number": "5285",
      "name": "若林 麗",
      "weight": "52.0kg",
      "tenjiTime": "6.64",
      "tilt": "-0.5",
      "st": ".14",
      "stFlag": "",
      "normalized": {
        "weightKg": 52,
        "tenjiSec": 6.64,
        "tiltDeg": -0.5,
        "stSec": 0.14,
        "isF": 0
      }
    }
  ]
}