{
  "date": "20240131",
  "pid": "01",
  "race": "10R",
  "source": "https://www.boatrace.jp/owpc/pc/race/beforeinfo?hd=20240131&jcd=01&rno=10",
  "mode": "beforeinfo",
  "generatedAt": "2025-11-07T04:53:04.314Z",
  "weather": {
    "weatherCode": 0,
    "windSpeed": 0,
    "windDirNum": null,
    "temperature": 7,
    "waterTemperature": 4,
    "waveHeight": 0,
    "stabilizer": 0,
    "weatherText": null,
    "windDirection": null
  },
  "entries": [
    {
      "lane": 1,
      "number": "4518",
      "name": "大須賀 友",
      "weight": "52.0kg",
      "tenjiTime": "6.64",
      "tilt": "-0.5",
      "st": "F.04",
      "stFlag": "F",
      "normalized": {
        "weightKg": 52,
        "tenjiSec": 6.64,
        "tiltDeg": -0.5,
        "stSec": 0.0004,
        "isF": 1
      }
    },
    {
      "lane": 2,
      "number": "4420",
      "name": "津久井 拓也",
      "weight": "53.2kg",
      "tenjiTime": "6.76",
      "tilt": "-0.5",
      "st": ".03",
      "stFlag": "",
      "normalized": {
        "weightKg": 53.2,
        "tenjiSec": 6.76,
        "tiltDeg": -0.5,
        "stSec": 0.03,
        "isF": 0
      }
    },
    {
      "lane": 3,
      "number": "4512",
      "name": "高野 哲史",
      "weight": "52.0kg",
      "tenjiTime": "6.76",
      "tilt": "-0.5",
      "st": ".11",
      "stFlag": "",
      "normalized": {
        "weightKg": 52,
        "tenjiSec": 6.76,
        "tiltDeg": -0.5,
        "stSec": 0.11,
        "isF": 0
      }
    },
    {
      "lane": 4,
      "number": "4949",
      "name": "横田 貴満",
      "weight": "51.5kg",
      "tenjiTime": "6.67",
      "tilt": "-0.5",
      "st": "F.01",
      "stFlag": "F",
      "normalized": {
        "weightKg": 51.5,
        "tenjiSec": 6.67,
        "tiltDeg": -0.5,
        "stSec": 0.0001,
        "isF": 1
      }
    },
    {
      "lane": 5,
      "number": "3268",
      "name": "森 竜也",
      "weight": "52.0kg",
      "tenjiTime": "6.65",
      "tilt": "-0.5",
      "st": ".04",
      "stFlag": "",
      "normalized": {
        "weightKg": 52,
        "tenjiSec": 6.65,
        "tiltDeg": -0.5,
        "stSec": 0.04,
        "isF": 0
      }
    },
    {
      "lane": 6,
      "number": "3912",
      "name": "川原 正明",
      "weight": "52.8kg",
      "tenjiTime": "6.73",
      "tilt": "-0.5",
      "st": ".13",
      "stFlag": "",
      "normalized": {
        "weightKg": 52.8,
        "tenjiSec": 6.73,
        "tiltDeg": -0.5,
        "stSec": 0.13,
        "isF": 0
      }
    }
  ]
}